nest_sdk_python_test_v2/__init__.py
nest_sdk_python_test_v2/_hooks/__init__.py
nest_sdk_python_test_v2/_hooks/sdkhooks.py
nest_sdk_python_test_v2/_hooks/types.py
nest_sdk_python_test_v2/_version.py
nest_sdk_python_test_v2/basesdk.py
nest_sdk_python_test_v2/github.py
nest_sdk_python_test_v2/httpclient.py
nest_sdk_python_test_v2/models/__init__.py
nest_sdk_python_test_v2/models/apierror.py
nest_sdk_python_test_v2/models/chapterschema.py
nest_sdk_python_test_v2/models/committeeschema.py
nest_sdk_python_test_v2/models/eventschema.py
nest_sdk_python_test_v2/models/get_userop.py
nest_sdk_python_test_v2/models/issueschema.py
nest_sdk_python_test_v2/models/labelschema.py
nest_sdk_python_test_v2/models/list_chaptersop.py
nest_sdk_python_test_v2/models/list_committeesop.py
nest_sdk_python_test_v2/models/list_eventsop.py
nest_sdk_python_test_v2/models/list_issuesop.py
nest_sdk_python_test_v2/models/list_labelsop.py
nest_sdk_python_test_v2/models/list_organizationsop.py
nest_sdk_python_test_v2/models/list_projectsop.py
nest_sdk_python_test_v2/models/list_releasesop.py
nest_sdk_python_test_v2/models/list_repositoriesop.py
nest_sdk_python_test_v2/models/list_usersop.py
nest_sdk_python_test_v2/models/no_response_error.py
nest_sdk_python_test_v2/models/organizationschema.py
nest_sdk_python_test_v2/models/pagedchapterschema.py
nest_sdk_python_test_v2/models/pagedcommitteeschema.py
nest_sdk_python_test_v2/models/pagedeventschema.py
nest_sdk_python_test_v2/models/pagedissueschema.py
nest_sdk_python_test_v2/models/pagedlabelschema.py
nest_sdk_python_test_v2/models/pagedorganizationschema.py
nest_sdk_python_test_v2/models/pagedprojectschema.py
nest_sdk_python_test_v2/models/pagedreleaseschema.py
nest_sdk_python_test_v2/models/pagedrepositoryschema.py
nest_sdk_python_test_v2/models/pageduserschema.py
nest_sdk_python_test_v2/models/projectlevel.py
nest_sdk_python_test_v2/models/projectschema.py
nest_sdk_python_test_v2/models/releaseschema.py
nest_sdk_python_test_v2-1.0.0.dist-info/METADATA
nest_sdk_python_test_v2-1.0.0.dist-info/WHEEL
nest_sdk_python_test_v2-1.0.0.dist-info/RECORD
